CHANGELOG.md
LICENSE
MANIFEST.in
README.md
VERSION
mkdocs.yml
setup.py
assets/final_video.mp4
assets/flort-logo.png
assets/flort.png
assets/flort2.png
assets/flort3.png
assets/flort4.png
docs/changelog.md
docs/contributing.md
docs/examples.md
docs/filtering.md
docs/index.md
docs/installation.md
docs/output-formats.md
docs/quickstart.md
docs/troubleshooting.md
docs/ui-guide.md
docs/usage.md
docs/api/core.md
docs/api/files.md
docs/api/overview.md
docs/api/utils.md
flort/__init__.py
flort/__main__.py
flort/assets.py
flort/cli.py
flort/concatenate_files.py
flort/curses_selector.py
flort/python_outline.py
flort/simple_selector.py
flort/traverse.py
flort/utils.py
flort/validation.py
flort/wrapper.py
tests/__init__.py
tests/test-ui.py
tests/test_flort.py
tests/test_ignore/file2.py
tests/test_no_ignore/file4.py