Metadata-Version: 2.4
Name: flort
Version: 0.1.29
Summary: File Concatenation and Project Overview Tool for LLM preparation
Home-page: https://github.com/watkinlabs/flort
Author: Chris Watkins
Author-email: chris@watkinslabs.com
License: BSD-3-Clause
Project-URL: Homepage, https://github.com/watkinslabs/flort
Project-URL: Documentation, https://watkinslabs.github.io/flort
Project-URL: Repository, https://github.com/watkinslabs/flort.git
Project-URL: Bug Tracker, https://github.com/watkinslabs/flort/issues
Project-URL: Discussions, https://github.com/watkinslabs/flort/discussions
Project-URL: Changelog, https://github.com/watkinslabs/flort/blob/main/CHANGELOG.md
Project-URL: Logo, https://raw.githubusercontent.com/watkinslabs/flort/main/assets/flort-logo.png
Keywords: file concatenation,project overview,LLM preparation,code analysis,documentation
Classifier: Development Status :: 5 - Production/Stable
Classifier: Environment :: Console
Classifier: Environment :: Console :: Curses
Classifier: Intended Audience :: Developers
Classifier: Intended Audience :: System Administrators
Classifier: License :: OSI Approved :: BSD License
Classifier: Operating System :: OS Independent
Classifier: Operating System :: POSIX :: Linux
Classifier: Operating System :: Microsoft :: Windows
Classifier: Operating System :: MacOS
Classifier: Programming Language :: Python :: 3
Classifier: Programming Language :: Python :: 3.6
Classifier: Programming Language :: Python :: 3.7
Classifier: Programming Language :: Python :: 3.8
Classifier: Programming Language :: Python :: 3.9
Classifier: Programming Language :: Python :: 3.10
Classifier: Programming Language :: Python :: 3.11
Classifier: Programming Language :: Python :: 3.12
Classifier: Programming Language :: Python :: 3.13
Classifier: Topic :: Documentation
Classifier: Topic :: Software Development :: Documentation
Classifier: Topic :: Software Development :: Libraries :: Python Modules
Classifier: Topic :: System :: Archiving
Classifier: Topic :: Text Processing
Classifier: Topic :: Utilities
Requires-Python: >=3.6
License-File: LICENSE
Requires-Dist: windows-curses; platform_system == "Windows"
Provides-Extra: dev
Requires-Dist: pytest>=6.0; extra == "dev"
Requires-Dist: pytest-cov>=2.0; extra == "dev"
Requires-Dist: mkdocs-material>=9.0; extra == "dev"
Provides-Extra: docs
Requires-Dist: mkdocs-material>=9.0; extra == "docs"
Requires-Dist: mkdocs-minify-plugin>=0.7; extra == "docs"
Requires-Dist: mkdocstrings[python]>=0.20; extra == "docs"
Dynamic: author
Dynamic: author-email
Dynamic: classifier
Dynamic: description
Dynamic: description-content-type
Dynamic: home-page
Dynamic: keywords
Dynamic: license
Dynamic: license-file
Dynamic: project-url
Dynamic: provides-extra
Dynamic: requires-dist
Dynamic: requires-python
Dynamic: summary
